multi_imbalance/__init__.py
multi_imbalance/datasets/__init__.py
multi_imbalance/datasets/_data_loader.py
multi_imbalance/datasets/tests/__init__.py
multi_imbalance/datasets/tests/test_data_loader.py
multi_imbalance/ensemble/__init__.py
multi_imbalance/ensemble/ecoc.py
multi_imbalance/ensemble/mrbbagging.py
multi_imbalance/ensemble/ovo.py
multi_imbalance/ensemble/soup_bagging.py
multi_imbalance/ensemble/tests/__init__.py
multi_imbalance/ensemble/tests/test_ecoc.py
multi_imbalance/ensemble/tests/test_mrbbagging.py
multi_imbalance/ensemble/tests/test_ovo.py
multi_imbalance/ensemble/tests/test_soupbagging.py
multi_imbalance/resampling/__init__.py
multi_imbalance/resampling/global_cs.py
multi_imbalance/resampling/mdo.py
multi_imbalance/resampling/soup.py
multi_imbalance/resampling/spider.py
multi_imbalance/resampling/static_smote.py
multi_imbalance/resampling/tests/__init__.py
multi_imbalance/resampling/tests/test_globalcs.py
multi_imbalance/resampling/tests/test_mdo.py
multi_imbalance/resampling/tests/test_soup.py
multi_imbalance/resampling/tests/test_spider.py
multi_imbalance/resampling/tests/test_static_smote.py
multi_imbalance/utils/__init__.py
multi_imbalance/utils/array_util.py
multi_imbalance/utils/data.py
multi_imbalance/utils/metrics.py
multi_imbalance/utils/min_int_maj.py
multi_imbalance/utils/plot.py
multi_imbalance-0.0.12.dist-info/LICENSE
multi_imbalance-0.0.12.dist-info/METADATA
multi_imbalance-0.0.12.dist-info/WHEEL
multi_imbalance-0.0.12.dist-info/top_level.txt
multi_imbalance-0.0.12.dist-info/RECORD
