Metadata-Version: 2.1
Name: multi-imbalance
Version: 0.0.12
Summary: Python package for tackling multiclass imbalance problems.
Home-page: https://github.com/damian-horna/multi-imbalance
Author: Damian Horna, Kamil Pluciński, Hanna Klimczak, Jacek Grycza
Author-email: horna.damian@gmail.com
License: UNKNOWN
Platform: UNKNOWN
Classifier: Programming Language :: Python :: 3
Classifier: License :: OSI Approved :: MIT License
Classifier: Operating System :: OS Independent
Classifier: Topic :: Software Development
Classifier: Topic :: Scientific/Engineering
Classifier: Programming Language :: Python :: 3.6
Classifier: Programming Language :: Python :: 3.7
Classifier: Programming Language :: Python :: 3.8
Requires-Dist: numpy (>=1.17.0)
Requires-Dist: scikit-learn (>=0.21.3)
Requires-Dist: pandas (>=0.25.1)
Requires-Dist: pytest (>=5.1.2)
Requires-Dist: imbalanced-learn (>=0.6.1)
Requires-Dist: coverage (>=5.1)
Requires-Dist: pytest-cov (>=2.8.1)
Requires-Dist: IPython (>=7.13.0)
Requires-Dist: seaborn (>=0.10.1)
Requires-Dist: matplotlib (>=3.2.1)
